z3c/recipe/mkdir/README.rst
z3c/recipe/mkdir/__init__.py
z3c/recipe/mkdir/regression.txt
z3c/recipe/mkdir/tests.py
z3c_recipe_mkdir-2.0.dist-info/LICENSE.txt
z3c_recipe_mkdir-2.0.dist-info/METADATA
z3c_recipe_mkdir-2.0.dist-info/WHEEL
z3c_recipe_mkdir-2.0.dist-info/entry_points.txt
z3c_recipe_mkdir-2.0.dist-info/top_level.txt
z3c_recipe_mkdir-2.0.dist-info/RECORD
