Metadata-Version: 2.2
Name: z3c.recipe.mkdir
Version: 2.0
Summary: Buildout recipe to create directories.
Home-page: https://github.com/zopefoundation/z3c.recipe.mkdir
Author: Uli Fouquet
Author-email: grok-dev@zope.org
License: ZPL-2.1
Keywords: buildout directory folder mkdir
Classifier: Development Status :: 3 - Alpha
Classifier: Framework :: Buildout
Classifier: Programming Language :: Python
Classifier: Programming Language :: Python :: 3
Classifier: Programming Language :: Python :: 3.9
Classifier: Programming Language :: Python :: 3.10
Classifier: Programming Language :: Python :: 3.11
Classifier: Programming Language :: Python :: 3.12
Classifier: Programming Language :: Python :: 3.13
Classifier: Programming Language :: Python :: Implementation :: CPython
Classifier: Programming Language :: Python :: Implementation :: PyPy
Classifier: Topic :: Software Development :: Libraries :: Python Modules
Classifier: License :: OSI Approved :: Zope Public License
Requires-Python: >=3.9
License-File: LICENSE.txt
Requires-Dist: setuptools
Requires-Dist: zc.buildout>=1.5
Provides-Extra: test
Requires-Dist: zope.testing; extra == "test"
Requires-Dist: zope.testrunner>=6.4; extra == "test"
Provides-Extra: testing
Requires-Dist: zope.testing; extra == "testing"
Requires-Dist: zope.testrunner>=6.4; extra == "testing"
Provides-Extra: docs
Requires-Dist: Sphinx; extra == "docs"
Dynamic: author
Dynamic: author-email
Dynamic: classifier
Dynamic: description
Dynamic: home-page
Dynamic: keywords
Dynamic: license
Dynamic: provides-extra
Dynamic: requires-dist
Dynamic: requires-python
Dynamic: summary
